babylon_sts/__init__.py
babylon_sts/processor.py
babylon_sts-0.1.43.dist-info/LICENSE
babylon_sts-0.1.43.dist-info/METADATA
babylon_sts-0.1.43.dist-info/WHEEL
babylon_sts-0.1.43.dist-info/top_level.txt
babylon_sts-0.1.43.dist-info/RECORD
